[{"hsh":"620c5d66ff8daa963c8fbcd996ab6ab6","date":"2024-08-14","title":"今天感觉很精神","copyright":"澳洲魔蜥，瓦塔卡国家公园，澳大利亚 (© Yva Momatiuk and John Eastcott/Minden Pictures)","url_preview":"https://cn.bing.com/th?id=OHR.WatarrkaLizard_ZH-CN7974623468_UHD.jpg&rf=LaDigue_UHD.jpg&pid=hp&w=480&h=270&rs=1&c=4","url_1080":"https://cn.bing.com/th?id=OHR.WatarrkaLizard_ZH-CN7974623468_UHD.jpg&rf=LaDigue_UHD.jpg&pid=hp&w=1920&h=1080&rs=1&c=4","url_4k":"https://cn.bing.com/th?id=OHR.WatarrkaLizard_ZH-CN7974623468_UHD.jpg&rf=LaDigue_UHD.jpg&pid=hp&w=3840&h=2160&rs=1&c=4"},{"hsh":"6f2d6c18906edad183e24d4d9f05047b","date":"2024-08-13","title":"亚得里亚海高地","copyright":"特拉斯契卡自然公园悬崖，杜吉奥托克岛，克罗地亚 (© Ilija Ascic/Shutterstock)","url_preview":"https://cn.bing.com/th?id=OHR.DugiOtokCroatia_ZH-CN7791404392_UHD.jpg&rf=LaDigue_UHD.jpg&pid=hp&w=480&h=270&rs=1&c=4","url_1080":"https://cn.bing.com/th?id=OHR.DugiOtokCroatia_ZH-CN7791404392_UHD.jpg&rf=LaDigue_UHD.jpg&pid=hp&w=1920&h=1080&rs=1&c=4","url_4k":"https://cn.bing.com/th?id=OHR.DugiOtokCroatia_ZH-CN7791404392_UHD.jpg&rf=LaDigue_UHD.jpg&pid=hp&w=3840&h=2160&rs=1&c=4"},{"hsh":"5919ccd9fcfd4080850356bb9e756afd","date":"2024-08-12","title":"你的声音嘹亮而清晰","copyright":"非洲象，肯尼亚安博塞利国家公园 (© Ruzdi Ekenheim/Getty Images)","url_preview":"https://cn.bing.com/th?id=OHR.ElephantsAmboseli_ZH-CN7596989061_UHD.jpg&rf=LaDigue_UHD.jpg&pid=hp&w=480&h=270&rs=1&c=4","url_1080":"https://cn.bing.com/th?id=OHR.ElephantsAmboseli_ZH-CN7596989061_UHD.jpg&rf=LaDigue_UHD.jpg&pid=hp&w=1920&h=1080&rs=1&c=4","url_4k":"https://cn.bing.com/th?id=OHR.ElephantsAmboseli_ZH-CN7596989061_UHD.jpg&rf=LaDigue_UHD.jpg&pid=hp&w=3840&h=2160&rs=1&c=4"},{"hsh":"34ff672125739b2e78fe1e675318fbfc","date":"2024-08-11","title":"人迹罕至的路","copyright":"通往肯尼迪湖的木板路，温哥华岛，加拿大不列颠哥伦比亚省 (© EB Adventure Photography/Shutterstock)","url_preview":"https://cn.bing.com/th?id=OHR.TofinoVancouver_ZH-CN6920493172_UHD.jpg&rf=LaDigue_UHD.jpg&pid=hp&w=480&h=270&rs=1&c=4","url_1080":"https://cn.bing.com/th?id=OHR.TofinoVancouver_ZH-CN6920493172_UHD.jpg&rf=LaDigue_UHD.jpg&pid=hp&w=1920&h=1080&rs=1&c=4","url_4k":"https://cn.bing.com/th?id=OHR.TofinoVancouver_ZH-CN6920493172_UHD.jpg&rf=LaDigue_UHD.jpg&pid=hp&w=3840&h=2160&rs=1&c=4"},{"hsh":"81d99a6f0f1e170e00cfcc5efee7ac3b","date":"2024-08-10","title":"星空下的约书亚树","copyright":"约书亚树国家公园，加利福尼亚州，美国 (© Chris Moore - Exploring Light Photography/TANDEM Stills + Motion)","url_preview":"https://cn.bing.com/th?id=OHR.JoshuaTreeNP_ZH-CN5917576674_UHD.jpg&rf=LaDigue_UHD.jpg&pid=hp&w=480&h=270&rs=1&c=4","url_1080":"https://cn.bing.com/th?id=OHR.JoshuaTreeNP_ZH-CN5917576674_UHD.jpg&rf=LaDigue_UHD.jpg&pid=hp&w=1920&h=1080&rs=1&c=4","url_4k":"https://cn.bing.com/th?id=OHR.JoshuaTreeNP_ZH-CN5917576674_UHD.jpg&rf=LaDigue_UHD.jpg&pid=hp&w=3840&h=2160&rs=1&c=4"},{"hsh":"51e49c8c2f7c55e64729d66bf4a622e4","date":"2024-08-09","title":"弘扬土著文化","copyright":"库斯科附近的萨克塞华曼印加遗址，秘鲁 (© SL_Photography/Getty Images)","url_preview":"https://cn.bing.com/th?id=OHR.IncaRuinPeru_ZH-CN5068602301_UHD.jpg&rf=LaDigue_UHD.jpg&pid=hp&w=480&h=270&rs=1&c=4","url_1080":"https://cn.bing.com/th?id=OHR.IncaRuinPeru_ZH-CN5068602301_UHD.jpg&rf=LaDigue_UHD.jpg&pid=hp&w=1920&h=1080&rs=1&c=4","url_4k":"https://cn.bing.com/th?id=OHR.IncaRuinPeru_ZH-CN5068602301_UHD.jpg&rf=LaDigue_UHD.jpg&pid=hp&w=3840&h=2160&rs=1&c=4"},{"hsh":"5d00a2f23ffdf2ca432e81f68b565ab7","date":"2024-08-08","title":"小猫头鹰瞪了你一眼","copyright":"横斑腹小鸮，曼谷，泰国 (© Tfilm/Getty Images)","url_preview":"https://cn.bing.com/th?id=OHR.SpottedOwlet_ZH-CN0841935587_UHD.jpg&rf=LaDigue_UHD.jpg&pid=hp&w=480&h=270&rs=1&c=4","url_1080":"https://cn.bing.com/th?id=OHR.SpottedOwlet_ZH-CN0841935587_UHD.jpg&rf=LaDigue_UHD.jpg&pid=hp&w=1920&h=1080&rs=1&c=4","url_4k":"https://cn.bing.com/th?id=OHR.SpottedOwlet_ZH-CN0841935587_UHD.jpg&rf=LaDigue_UHD.jpg&pid=hp&w=3840&h=2160&rs=1&c=4"},{"hsh":"54a253dfdecacb23dc0c3d7ba5116088","date":"2024-08-07","title":"不止是航海需要它","copyright":"圣约瑟夫北码头内灯和外灯，密歇根州，美国 (© Kenneth Keifer/Getty Images)","url_preview":"https://cn.bing.com/th?id=OHR.MichiganLighthouse_ZH-CN0581377136_UHD.jpg&rf=LaDigue_UHD.jpg&pid=hp&w=480&h=270&rs=1&c=4","url_1080":"https://cn.bing.com/th?id=OHR.MichiganLighthouse_ZH-CN0581377136_UHD.jpg&rf=LaDigue_UHD.jpg&pid=hp&w=1920&h=1080&rs=1&c=4","url_4k":"https://cn.bing.com/th?id=OHR.MichiganLighthouse_ZH-CN0581377136_UHD.jpg&rf=LaDigue_UHD.jpg&pid=hp&w=3840&h=2160&rs=1&c=4"},{"hsh":"315a0b69d5c6b77f08a42f25ec2a4c3c","date":"2024-08-06","title":"迎合所有人口味的景点","copyright":"莫洛基尼，毛伊岛，夏威夷，美国 (© Douglas Peebles/eStock Photo)","url_preview":"https://cn.bing.com/th?id=OHR.MolokiniHawaii_ZH-CN0375050872_UHD.jpg&rf=LaDigue_UHD.jpg&pid=hp&w=480&h=270&rs=1&c=4","url_1080":"https://cn.bing.com/th?id=OHR.MolokiniHawaii_ZH-CN0375050872_UHD.jpg&rf=LaDigue_UHD.jpg&pid=hp&w=1920&h=1080&rs=1&c=4","url_4k":"https://cn.bing.com/th?id=OHR.MolokiniHawaii_ZH-CN0375050872_UHD.jpg&rf=LaDigue_UHD.jpg&pid=hp&w=3840&h=2160&rs=1&c=4"},{"hsh":"2721cf73c9f92f7a2824d625cddcb5b7","date":"2024-08-05","title":"一片紫色的海洋","copyright":"薰衣草田，赫特福德郡 ，英格兰，英国 (© George W Johnson/Getty Images)","url_preview":"https://cn.bing.com/th?id=OHR.HertfordshireLavender_ZH-CN9771886404_UHD.jpg&rf=LaDigue_UHD.jpg&pid=hp&w=480&h=270&rs=1&c=4","url_1080":"https://cn.bing.com/th?id=OHR.HertfordshireLavender_ZH-CN9771886404_UHD.jpg&rf=LaDigue_UHD.jpg&pid=hp&w=1920&h=1080&rs=1&c=4","url_4k":"https://cn.bing.com/th?id=OHR.HertfordshireLavender_ZH-CN9771886404_UHD.jpg&rf=LaDigue_UHD.jpg&pid=hp&w=3840&h=2160&rs=1&c=4"},{"hsh":"ff9d027fac843a444a7e1216826e07d3","date":"2024-08-04","title":"我是你的朋友","copyright":"黑斑羚和红嘴牛椋鸟，南非 (© Matrishva Vyas/Getty Images)","url_preview":"https://cn.bing.com/th?id=OHR.ImpalaOxpecker_ZH-CN9652434873_UHD.jpg&rf=LaDigue_UHD.jpg&pid=hp&w=480&h=270&rs=1&c=4","url_1080":"https://cn.bing.com/th?id=OHR.ImpalaOxpecker_ZH-CN9652434873_UHD.jpg&rf=LaDigue_UHD.jpg&pid=hp&w=1920&h=1080&rs=1&c=4","url_4k":"https://cn.bing.com/th?id=OHR.ImpalaOxpecker_ZH-CN9652434873_UHD.jpg&rf=LaDigue_UHD.jpg&pid=hp&w=3840&h=2160&rs=1&c=4"},{"hsh":"99468bf9a6e8b828597229af489a5235","date":"2024-08-03","title":"武隆景区的“三生三世”","copyright":"天生三桥，重庆武隆岩溶国家地质公园，中国 (© Pav-Pro Photography Ltd/Shutterstock)","url_preview":"https://cn.bing.com/th?id=OHR.WulongKarst_ZH-CN9386528384_UHD.jpg&rf=LaDigue_UHD.jpg&pid=hp&w=480&h=270&rs=1&c=4","url_1080":"https://cn.bing.com/th?id=OHR.WulongKarst_ZH-CN9386528384_UHD.jpg&rf=LaDigue_UHD.jpg&pid=hp&w=1920&h=1080&rs=1&c=4","url_4k":"https://cn.bing.com/th?id=OHR.WulongKarst_ZH-CN9386528384_UHD.jpg&rf=LaDigue_UHD.jpg&pid=hp&w=3840&h=2160&rs=1&c=4"},{"hsh":"29d6b3b2cf0d9c670db4844336128246","date":"2024-08-02","title":"彩虹之下的某个地方","copyright":"象鼻湾，维尔京群岛国家公园，圣约翰岛 (© wheatley/Getty Images)","url_preview":"https://cn.bing.com/th?id=OHR.TrunkBay_ZH-CN9268190655_UHD.jpg&rf=LaDigue_UHD.jpg&pid=hp&w=480&h=270&rs=1&c=4","url_1080":"https://cn.bing.com/th?id=OHR.TrunkBay_ZH-CN9268190655_UHD.jpg&rf=LaDigue_UHD.jpg&pid=hp&w=1920&h=1080&rs=1&c=4","url_4k":"https://cn.bing.com/th?id=OHR.TrunkBay_ZH-CN9268190655_UHD.jpg&rf=LaDigue_UHD.jpg&pid=hp&w=3840&h=2160&rs=1&c=4"},{"hsh":"b3b6da6da5be752a0fc41e3102052908","date":"2024-08-01","title":"物价喜人","copyright":"卡普泰湖水上市场，兰加马蒂，孟加拉 (© Azim Khan Ronnie/Amazing Aerial Agency)","url_preview":"https://cn.bing.com/th?id=OHR.KaptaiLake_ZH-CN9085738832_UHD.jpg&rf=LaDigue_UHD.jpg&pid=hp&w=480&h=270&rs=1&c=4","url_1080":"https://cn.bing.com/th?id=OHR.KaptaiLake_ZH-CN9085738832_UHD.jpg&rf=LaDigue_UHD.jpg&pid=hp&w=1920&h=1080&rs=1&c=4","url_4k":"https://cn.bing.com/th?id=OHR.KaptaiLake_ZH-CN9085738832_UHD.jpg&rf=LaDigue_UHD.jpg&pid=hp&w=3840&h=2160&rs=1&c=4"}]