[{"hsh":"99468bf9a6e8b828597229af489a5235","date":"2024-08-03","title":"武隆景区的“三生三世”","copyright":"天生三桥，重庆武隆岩溶国家地质公园，中国 (© Pav-Pro Photography Ltd/Shutterstock)","url_preview":"https://cn.bing.com/th?id=OHR.WulongKarst_ZH-CN9386528384_UHD.jpg&rf=LaDigue_UHD.jpg&pid=hp&w=480&h=270&rs=1&c=4","url_1080":"https://cn.bing.com/th?id=OHR.WulongKarst_ZH-CN9386528384_UHD.jpg&rf=LaDigue_UHD.jpg&pid=hp&w=1920&h=1080&rs=1&c=4","url_4k":"https://cn.bing.com/th?id=OHR.WulongKarst_ZH-CN9386528384_UHD.jpg&rf=LaDigue_UHD.jpg&pid=hp&w=3840&h=2160&rs=1&c=4"},{"hsh":"29d6b3b2cf0d9c670db4844336128246","date":"2024-08-02","title":"彩虹之下的某个地方","copyright":"象鼻湾，维尔京群岛国家公园，圣约翰岛 (© wheatley/Getty Images)","url_preview":"https://cn.bing.com/th?id=OHR.TrunkBay_ZH-CN9268190655_UHD.jpg&rf=LaDigue_UHD.jpg&pid=hp&w=480&h=270&rs=1&c=4","url_1080":"https://cn.bing.com/th?id=OHR.TrunkBay_ZH-CN9268190655_UHD.jpg&rf=LaDigue_UHD.jpg&pid=hp&w=1920&h=1080&rs=1&c=4","url_4k":"https://cn.bing.com/th?id=OHR.TrunkBay_ZH-CN9268190655_UHD.jpg&rf=LaDigue_UHD.jpg&pid=hp&w=3840&h=2160&rs=1&c=4"},{"hsh":"b3b6da6da5be752a0fc41e3102052908","date":"2024-08-01","title":"物价喜人","copyright":"卡普泰湖水上市场，兰加马蒂，孟加拉 (© Azim Khan Ronnie/Amazing Aerial Agency)","url_preview":"https://cn.bing.com/th?id=OHR.KaptaiLake_ZH-CN9085738832_UHD.jpg&rf=LaDigue_UHD.jpg&pid=hp&w=480&h=270&rs=1&c=4","url_1080":"https://cn.bing.com/th?id=OHR.KaptaiLake_ZH-CN9085738832_UHD.jpg&rf=LaDigue_UHD.jpg&pid=hp&w=1920&h=1080&rs=1&c=4","url_4k":"https://cn.bing.com/th?id=OHR.KaptaiLake_ZH-CN9085738832_UHD.jpg&rf=LaDigue_UHD.jpg&pid=hp&w=3840&h=2160&rs=1&c=4"}]